mcp_toolhouse/__init__.py
mcp_toolhouse-0.1.0.dist-info/METADATA
mcp_toolhouse-0.1.0.dist-info/WHEEL
mcp_toolhouse-0.1.0.dist-info/entry_points.txt
mcp_toolhouse-0.1.0.dist-info/RECORD
